h5cube/__init__.py
h5cube/h5cube.py
h5cube/test/__init__.py
h5cube/test/h5cube_cmdline.py
h5cube/test/h5cube_functions.py
h5cube-0.3.dist-info/DESCRIPTION.rst
h5cube-0.3.dist-info/METADATA
h5cube-0.3.dist-info/RECORD
h5cube-0.3.dist-info/WHEEL
h5cube-0.3.dist-info/entry_points.txt
h5cube-0.3.dist-info/metadata.json
h5cube-0.3.dist-info/top_level.txt
