Metadata-Version: 2.0
Name: h5cube
Version: 0.3
Summary: Gaussian CUBE File Compression Utility
Home-page: https://www.github.com/bskinn/h5cube
Author: Brian Skinn
Author-email: bskinn@alum.mit.edu
License: MIT License
Platform: UNKNOWN
Classifier: License :: OSI Approved :: MIT License
Classifier: Natural Language :: English
Classifier: Environment :: Console
Classifier: Intended Audience :: Science/Research
Classifier: Operating System :: OS Independent
Classifier: Programming Language :: Python :: 3 :: Only
Classifier: Programming Language :: Python :: 3.4
Classifier: Programming Language :: Python :: 3.5
Classifier: Topic :: Scientific/Engineering
Classifier: Topic :: System :: Archiving :: Compression
Classifier: Topic :: Utilities
Classifier: Development Status :: 4 - Beta
Requires: h5py (>=2.4)
Requires: numpy (>=1.8)
Provides: h5cube
